LICENSE
MANIFEST.in
README.md
requirements.txt
setup.py
kubetwo/__init__.py
kubetwo/ansible.py
kubetwo/common.py
kubetwo/config.py
kubetwo/create.py
kubetwo/delete.py
kubetwo/exception.py
kubetwo/main.py
kubetwo/model.py
kubetwo/scale.py
kubetwo/terraform.py
kubetwo/validator.py
kubetwo.egg-info/PKG-INFO
kubetwo.egg-info/SOURCES.txt
kubetwo.egg-info/dependency_links.txt
kubetwo.egg-info/entry_points.txt
kubetwo.egg-info/requires.txt
kubetwo.egg-info/top_level.txt
kubetwo/ansible_template/deploy_sample.yml
kubetwo/ansible_template/fetch_kubeconfig.yml
kubetwo/ansible_template/inventory.yml
kubetwo/ansible_template/setup_kubeconfig.yml
kubetwo/data/distro_info.json
kubetwo/data/node_info.txt.j2
kubetwo/data/validation_result.txt.j2
kubetwo/terraform_template/instance.tf
kubetwo/terraform_template/network.tf
kubetwo/terraform_template/outputs.tf
kubetwo/terraform_template/provider.tf
kubetwo/terraform_template/security.tf.j2
kubetwo/terraform_template/variables.tf.j2
kubetwo/terraform_template/load_balancer/main.tf
kubetwo/terraform_template/load_balancer/outputs.tf
kubetwo/terraform_template/load_balancer/variables.tf.j2
kubetwo/terraform_template/security_group/main.tf
kubetwo/terraform_template/security_group/outputs.tf
kubetwo/terraform_template/security_group/variables.tf
kubetwo/terraform_template/vpc/main.tf
kubetwo/terraform_template/vpc/outputs.tf
kubetwo/terraform_template/vpc/variables.tf