Metadata-Version: 2.1
Name: kubetwo
Version: 0.4.0
Summary: Simple CLI tool to create Kubernetes cluster on AWS EC2.
Home-page: https://github.com/opeco17/kubetwo
Author: opeco17
License: Apache License 2.0
Keywords: kubetwo kube-two kube2 kube-2
Platform: UNKNOWN
Classifier: License :: OSI Approved :: Apache Software License
Classifier: Programming Language :: Python :: 3
Classifier: Programming Language :: Python :: 3.6
Classifier: Programming Language :: Python :: 3.7
Classifier: Programming Language :: Python :: 3.8
Classifier: Programming Language :: Python :: 3.9
Classifier: Intended Audience :: Developers
Classifier: Intended Audience :: Information Technology
Requires-Python: >= 3.6
